ip_api_py/__init__.py
ip_api_py/dt.py
ip_api_py/ip_api.py
ip_api_py/test_ip.py
ip_api_py-0.1.2.dist-info/LICENSE
ip_api_py-0.1.2.dist-info/WHEEL
ip_api_py-0.1.2.dist-info/METADATA
ip_api_py-0.1.2.dist-info/RECORD
